{
  "menu": [
    {
      "name": "Dashboard",
      "badge": "",
      "badgeClass": "badge badge-light-warning badge-pill ml-auto mr-1",
      "icon": "home",
      "slug": "",
      "url":"admin"
    },
    {
        "url": "admin/roles",
        "name": "Roles",
        "icon": "users",
        "slug": "roles"
      },
    {
        "url": "admin/permissions",
        "name": "Permissions",
        "icon": "users",
        "slug": "permissions"
      },
      {
          "url": "admin/patients",
          "name": "Children",
          "icon": "users",
          "slug": "children"
        }

  ]
}
